{
  "title": "When You're Seated Next To The Girl You Have a Crush On",
  "description": "A summary of the story between Kenjiro and his crsuh Tozaki-san. Twitter source: https://twitter.com/i/events/1282272053907742722, Author's twitter: https://twitter.com/saku5885",
  "artist": "@saku5885",
  "author": "@saku5885",
  "cover": "https://pbs.twimg.com/media/EcexqBJU8AAiDSX?format=jpg&name=small",
  "chapters": {
    "1": {
      "title": "1",
      "volume": "",
      "last_updated": "1624864769",
      "groups": {
        "Kanojo Scans": [
          "https://i.redd.it/n5mdgumghy771.png",
          "https://i.redd.it/5f8bczmghy771.png",
          "https://i.redd.it/7i58ayuihy771.png"
        ]
      }
    },
    "2": {
      "title": "2",
      "volume": "",
      "last_updated": "1627630930",
      "groups": {
        "Kanojo Scans": [
          "https://i.redd.it/srw9jbf80be71.png",
          "https://i.redd.it/l7qqegf80be71.png",
          "https://i.redd.it/tly7f7f80be71.png",
          "https://i.redd.it/6c6a96y90be71.png"
        ]
      }
    },
    "3": {
      "title": "3",
      "volume": "",
      "last_updated": "1627690632",
      "groups": {
        "Kanojo Scans": [
          "https://i.redd.it/aey7p1qkxfe71.png",
          "https://i.redd.it/ecnljypkxfe71.png",
          "https://i.redd.it/7jqxifsmxfe71.png"
        ]
      }
    },
    "4": {
      "title": "4",
      "volume": "",
      "last_updated": "1627797230",
      "groups": {
        "Kanojo Scans": [
          "https://i.redd.it/7nwz5tv3roe71.png",
          "https://i.redd.it/g6kn7lv3roe71.png",
          "https://i.redd.it/s6jt34m5roe71.png"
        ]
      }
    },
    "5": {
      "title": "5",
      "volume": "",
      "last_updated": "1627960546",
      "groups": {
        "Kanojo Scans": [
          "https://i.redd.it/rsxmy9ub6we71.png",
          "https://i.redd.it/h9wr15ub6we71.png"
        ]
      }
    },
    "6": {
      "title": "6",
      "volume": "",
      "last_updated": "1627974245",
      "groups": {
        "Kanojo Scans": [
          "https://i.redd.it/y5anp4lzc3f71.png",
          "https://i.redd.it/l9cs8alzc3f71.png",
          "https://i.redd.it/c2rhw980d3f71.png"
        ]
      }
    }
  }
}